nppm-0.1.2.dist-info/DESCRIPTION.rst
nppm-0.1.2.dist-info/WHEEL
nppm-0.1.2.dist-info/entry_points.txt
nppm-0.1.2.dist-info/metadata.json
nppm-0.1.2.dist-info/METADATA
nppm-0.1.2.dist-info/RECORD
nppm-0.1.2.dist-info/top_level.txt
nppm/__init__.py
nppm/util.py
nppm/main.py
nppm/commands/__init__.py
nppm/commands/python.py
nppm/commands/init.py
nppm/commands/install.py
