Metadata-Version: 2.0
Name: nppm
Version: 0.1.2
Summary: An npm-like tool for Python projects
Home-page: https://github.com/emallson/nppm
Author: J David Smith
Author-email: emallson@atlanis.net
License: GPL
Keywords: development
Platform: UNKNOWN
Classifier: Development Status :: 3 - Alpha
Classifier: Intended Audience :: Developers
Classifier: Topic :: Software Development :: Build Tools
Classifier: License :: OSI Approved :: GNU General Public License v3 or later (GPLv3+)
Classifier: Programming Language :: Python :: 3
Requires-Dist: pip
Requires-Dist: ipython
Requires-Dist: semver
